flask_msgspec/__init__.py
flask_msgspec/core.py
flask_msgspec-0.0.2.dist-info/LICENSE
flask_msgspec-0.0.2.dist-info/METADATA
flask_msgspec-0.0.2.dist-info/WHEEL
flask_msgspec-0.0.2.dist-info/RECORD
