Metadata-Version: 2.1
Name: flask-msgspec
Version: 0.0.2
Summary: msgspec integration for Flask
Home-page: https://github.com/floxay/flask-msgspec
License: MIT
Keywords: api,http,flask,msgspec,validation
Author: Huba Tuba
Author-email: hubasolttuba@gmail.com
Requires-Python: >=3.8,<4
Classifier: Environment :: Web Environment
Classifier: Framework :: Flask
Classifier: Intended Audience :: Developers
Classifier: License :: OSI Approved :: MIT License
Classifier: Operating System :: OS Independent
Classifier: Programming Language :: Python
Classifier: Programming Language :: Python :: 3
Classifier: Programming Language :: Python :: 3.8
Classifier: Programming Language :: Python :: 3.9
Classifier: Programming Language :: Python :: 3.10
Classifier: Programming Language :: Python :: 3.11
Classifier: Programming Language :: Python :: 3 :: Only
Classifier: Topic :: Internet :: WWW/HTTP
Classifier: Topic :: Software Development
Classifier: Topic :: Software Development :: Libraries
Classifier: Topic :: Software Development :: Libraries :: Python Modules
Classifier: Typing :: Typed
Requires-Dist: Flask (>=2.2.0,<3)
Requires-Dist: msgspec (>=0.17.0,<1)
Project-URL: Changelog, https://github.com/floxay/flask-msgspec/releases
Project-URL: Issue Tracker, https://github.com/floxay/flask-msgspec/issues
Project-URL: Repository, https://github.com/floxay/flask-msgspec
